cloudpy/__init__.py
cloudpy/errors.py
cloudpy/numpy/__init__.py
cloudpy/numpy/monkey_patch.py
cloudpy/pandas/__init__.py
npc_internal/__init__.py
npc_internal/api.py
npc_internal/config.py
npc_internal/logger.py
npc_internal/monkey_patch.py
npc_internal/protocol.py
npc_internal/proxy.py
npc_internal/proxy_objects.py
npc_internal/test_monkey_patch.py
npc_internal/util.py
cloudpyio-0.0.23.dist-info/LICENSE
cloudpyio-0.0.23.dist-info/METADATA
cloudpyio-0.0.23.dist-info/WHEEL
cloudpyio-0.0.23.dist-info/top_level.txt
cloudpyio-0.0.23.dist-info/RECORD
